{"cameraMode":{"drawMode":0,"name":"Shaded","section":"Shading Mode"},"sceneLighting":true,"audioPlay":false,"sceneViewState":{"m_AlwaysRefresh":false,"showFog":true,"showSkybox":true,"showFlares":true,"showImageEffects":true,"showParticleSystems":true,"showVisualEffectGraphs":true,"m_FxEnabled":true},"in2DMode":false,"pivot":{"x":-12.708802223205567,"y":-8.627928733825684,"z":3.003709554672241},"rotation":{"x":0.24287204444408418,"y":-0.6269382834434509,"z":0.214959517121315,"w":0.7083498239517212},"size":8.951004028320313,"orthographic":false}